{"shard_id": "c05_replay_150_0118_sla1.5", "id": "c05_replay_150_0118_sla1.5", "base_id": "c05_replay_150_0118", "campus": 5, "size": 150, "condition": "sla1.5", "rows": {"edd": {"id": "c05_replay_150_0118_sla1.5", "base_id": "c05_replay_150_0118", "campus": 5, "size": 150, "condition": "sla1.5", "sla_multiplier": 1.5, "crew_multiplier": 1.0, "method": "edd", "seed": 301, "feasible": 1, "wwt": 0.0, "makespan": 89.0, "mean_flow": 3.981405333333334, "breach_share": 0.0, "breach_p1": null, "breach_p2": null, "breach_p3": 0.0, "breach_p4": null, "wall_seconds": 0.00025760335847735405}, "wspt": {"id": "c05_replay_150_0118_sla1.5", "base_id": "c05_replay_150_0118", "campus": 5, "size": 150, "condition": "sla1.5", "sla_multiplier": 1.5, "crew_multiplier": 1.0, "method": "wspt", "seed": 301, "feasible": 1, "wwt": 0.0, "makespan": 89.0, "mean_flow": 3.981405333333334, "breach_share": 0.0, "breach_p1": null, "breach_p2": null, "breach_p3": 0.0, "breach_p4": null, "wall_seconds": 0.0002621486783027649}, "atc": {"id": "c05_replay_150_0118_sla1.5", "base_id": "c05_replay_150_0118", "campus": 5, "size": 150, "condition": "sla1.5", "sla_multiplier": 1.5, "crew_multiplier": 1.0, "method": "atc", "seed": 301, "feasible": 1, "wwt": 0.0, "makespan": 89.0, "mean_flow": 3.981405333333334, "breach_share": 0.0, "breach_p1": null, "breach_p2": null, "breach_p3": 0.0, "breach_p4": null, "wall_seconds": 0.00029316265136003494}, "pfifo": {"id": "c05_replay_150_0118_sla1.5", "base_id": "c05_replay_150_0118", "campus": 5, "size": 150, "condition": "sla1.5", "sla_multiplier": 1.5, "crew_multiplier": 1.0, "method": "pfifo", "seed": 301, "feasible": 1, "wwt": 0.0, "makespan": 89.0, "mean_flow": 3.981405333333334, "breach_share": 0.0, "breach_p1": null, "breach_p2": null, "breach_p3": 0.0, "breach_p4": null, "wall_seconds": 0.00023633381351828575}, "mor": {"id": "c05_replay_150_0118_sla1.5", "base_id": "c05_replay_150_0118", "campus": 5, "size": 150, "condition": "sla1.5", "sla_multiplier": 1.5, "crew_multiplier": 1.0, "method": "mor", "seed": 301, "feasible": 1, "wwt": 0.0, "makespan": 89.0, "mean_flow": 3.981405333333334, "breach_share": 0.0, "breach_p1": null, "breach_p2": null, "breach_p3": 0.0, "breach_p4": null, "wall_seconds": 0.0002363370731472969}, "random": {"id": "c05_replay_150_0118_sla1.5", "base_id": "c05_replay_150_0118", "campus": 5, "size": 150, "condition": "sla1.5", "sla_multiplier": 1.5, "crew_multiplier": 1.0, "method": "random", "seed": 301, "feasible": 1, "wwt": 0.0, "makespan": 89.0, "mean_flow": 3.981405333333334, "breach_share": 0.0, "breach_p1": null, "breach_p2": null, "breach_p3": 0.0, "breach_p4": null, "wall_seconds": 0.00022549880668520927}, "v2rl301": {"id": "c05_replay_150_0118_sla1.5", "base_id": "c05_replay_150_0118", "campus": 5, "size": 150, "condition": "sla1.5", "sla_multiplier": 1.5, "crew_multiplier": 1.0, "method": "v2rl301", "seed": 301, "feasible": 1, "wwt": 0.0, "makespan": 89.0, "mean_flow": 3.981405333333334, "breach_share": 0.0, "breach_p1": null, "breach_p2": null, "breach_p3": 0.0, "breach_p4": null, "wall_seconds": 0.014965066686272621}, "v2rl302": {"id": "c05_replay_150_0118_sla1.5", "base_id": "c05_replay_150_0118", "campus": 5, "size": 150, "condition": "sla1.5", "sla_multiplier": 1.5, "crew_multiplier": 1.0, "method": "v2rl302", "seed": 302, "feasible": 1, "wwt": 0.0, "makespan": 89.0, "mean_flow": 3.981405333333334, "breach_share": 0.0, "breach_p1": null, "breach_p2": null, "breach_p3": 0.0, "breach_p4": null, "wall_seconds": 0.015004220884293318}, "v2rl303": {"id": "c05_replay_150_0118_sla1.5", "base_id": "c05_replay_150_0118", "campus": 5, "size": 150, "condition": "sla1.5", "sla_multiplier": 1.5, "crew_multiplier": 1.0, "method": "v2rl303", "seed": 303, "feasible": 1, "wwt": 0.0, "makespan": 89.0, "mean_flow": 3.981405333333334, "breach_share": 0.0, "breach_p1": null, "breach_p2": null, "breach_p3": 0.0, "breach_p4": null, "wall_seconds": 0.014601962640881538}}, "methods_expected": ["edd", "wspt", "atc", "pfifo", "mor", "random", "v2rl301", "v2rl302", "v2rl303"], "infeasible": [], "wall_seconds_total": 0.04810411483049393}