{"shard_id": "c05_replay_400_0100_sla1.5", "id": "c05_replay_400_0100_sla1.5", "base_id": "c05_replay_400_0100", "campus": 5, "size": 400, "condition": "sla1.5", "rows": {"edd": {"id": "c05_replay_400_0100_sla1.5", "base_id": "c05_replay_400_0100", "campus": 5, "size": 400, "condition": "sla1.5", "sla_multiplier": 1.5, "crew_multiplier": 1.0, "method": "edd", "seed": 301, "feasible": 1, "wwt": 0.0, "makespan": 112.73, "mean_flow": 4.246133500000001, "breach_share": 0.0, "breach_p1": null, "breach_p2": null, "breach_p3": 0.0, "breach_p4": 0.0, "wall_seconds": 0.0006434726528823376}, "wspt": {"id": "c05_replay_400_0100_sla1.5", "base_id": "c05_replay_400_0100", "campus": 5, "size": 400, "condition": "sla1.5", "sla_multiplier": 1.5, "crew_multiplier": 1.0, "method": "wspt", "seed": 301, "feasible": 1, "wwt": 0.0, "makespan": 112.73, "mean_flow": 4.2423835, "breach_share": 0.0, "breach_p1": null, "breach_p2": null, "breach_p3": 0.0, "breach_p4": 0.0, "wall_seconds": 0.0006564711220562458}, "atc": {"id": "c05_replay_400_0100_sla1.5", "base_id": "c05_replay_400_0100", "campus": 5, "size": 400, "condition": "sla1.5", "sla_multiplier": 1.5, "crew_multiplier": 1.0, "method": "atc", "seed": 301, "feasible": 1, "wwt": 0.0, "makespan": 112.73, "mean_flow": 4.2423835, "breach_share": 0.0, "breach_p1": null, "breach_p2": null, "breach_p3": 0.0, "breach_p4": 0.0, "wall_seconds": 0.0007902458310127258}, "pfifo": {"id": "c05_replay_400_0100_sla1.5", "base_id": "c05_replay_400_0100", "campus": 5, "size": 400, "condition": "sla1.5", "sla_multiplier": 1.5, "crew_multiplier": 1.0, "method": "pfifo", "seed": 301, "feasible": 1, "wwt": 0.0, "makespan": 112.73, "mean_flow": 4.246133500000001, "breach_share": 0.0, "breach_p1": null, "breach_p2": null, "breach_p3": 0.0, "breach_p4": 0.0, "wall_seconds": 0.0005930126644670963}, "mor": {"id": "c05_replay_400_0100_sla1.5", "base_id": "c05_replay_400_0100", "campus": 5, "size": 400, "condition": "sla1.5", "sla_multiplier": 1.5, "crew_multiplier": 1.0, "method": "mor", "seed": 301, "feasible": 1, "wwt": 0.0, "makespan": 112.73, "mean_flow": 4.258633499999999, "breach_share": 0.0, "breach_p1": null, "breach_p2": null, "breach_p3": 0.0, "breach_p4": 0.0, "wall_seconds": 0.0005774940364062786}, "random": {"id": "c05_replay_400_0100_sla1.5", "base_id": "c05_replay_400_0100", "campus": 5, "size": 400, "condition": "sla1.5", "sla_multiplier": 1.5, "crew_multiplier": 1.0, "method": "random", "seed": 301, "feasible": 1, "wwt": 0.0, "makespan": 112.73, "mean_flow": 4.2461335, "breach_share": 0.0, "breach_p1": null, "breach_p2": null, "breach_p3": 0.0, "breach_p4": 0.0, "wall_seconds": 0.000536617822945118}, "v2rl301": {"id": "c05_replay_400_0100_sla1.5", "base_id": "c05_replay_400_0100", "campus": 5, "size": 400, "condition": "sla1.5", "sla_multiplier": 1.5, "crew_multiplier": 1.0, "method": "v2rl301", "seed": 301, "feasible": 1, "wwt": 0.0, "makespan": 112.73, "mean_flow": 4.258633499999999, "breach_share": 0.0, "breach_p1": null, "breach_p2": null, "breach_p3": 0.0, "breach_p4": 0.0, "wall_seconds": 0.04109130799770355}, "v2rl302": {"id": "c05_replay_400_0100_sla1.5", "base_id": "c05_replay_400_0100", "campus": 5, "size": 400, "condition": "sla1.5", "sla_multiplier": 1.5, "crew_multiplier": 1.0, "method": "v2rl302", "seed": 302, "feasible": 1, "wwt": 0.0, "makespan": 112.73, "mean_flow": 4.258633499999999, "breach_share": 0.0, "breach_p1": null, "breach_p2": null, "breach_p3": 0.0, "breach_p4": 0.0, "wall_seconds": 0.04042871296405792}, "v2rl303": {"id": "c05_replay_400_0100_sla1.5", "base_id": "c05_replay_400_0100", "campus": 5, "size": 400, "condition": "sla1.5", "sla_multiplier": 1.5, "crew_multiplier": 1.0, "method": "v2rl303", "seed": 303, "feasible": 1, "wwt": 0.0, "makespan": 112.73, "mean_flow": 4.258633499999999, "breach_share": 0.0, "breach_p1": null, "breach_p2": null, "breach_p3": 0.0, "breach_p4": 0.0, "wall_seconds": 0.0410932800732553}}, "methods_expected": ["edd", "wspt", "atc", "pfifo", "mor", "random", "v2rl301", "v2rl302", "v2rl303"], "infeasible": [], "wall_seconds_total": 0.13099432084709406}