{"shard_id": "c12_replay_400_0064_m1.25", "id": "c12_replay_400_0064_m1.25", "base_id": "c12_replay_400_0064", "campus": 12, "size": 400, "condition": "crew1.25", "rows": {"edd": {"id": "c12_replay_400_0064_m1.25", "base_id": "c12_replay_400_0064", "campus": 12, "size": 400, "condition": "crew1.25", "sla_multiplier": 1.0, "crew_multiplier": 1.25, "method": "edd", "seed": 301, "feasible": 1, "wwt": 2154.1295999999998, "makespan": 166.7337, "mean_flow": 6.6146125, "breach_share": 0.0525, "breach_p1": 0.1652892561983471, "breach_p2": 0.0, "breach_p3": 0.013513513513513514, "breach_p4": 0.0, "wall_seconds": 0.0006468840874731541}, "wspt": {"id": "c12_replay_400_0064_m1.25", "base_id": "c12_replay_400_0064", "campus": 12, "size": 400, "condition": "crew1.25", "sla_multiplier": 1.0, "crew_multiplier": 1.25, "method": "wspt", "seed": 301, "feasible": 1, "wwt": 2154.1295999999998, "makespan": 166.7337, "mean_flow": 6.6146125, "breach_share": 0.0525, "breach_p1": 0.1652892561983471, "breach_p2": 0.0, "breach_p3": 0.013513513513513514, "breach_p4": 0.0, "wall_seconds": 0.0006411229260265827}, "atc": {"id": "c12_replay_400_0064_m1.25", "base_id": "c12_replay_400_0064", "campus": 12, "size": 400, "condition": "crew1.25", "sla_multiplier": 1.0, "crew_multiplier": 1.25, "method": "atc", "seed": 301, "feasible": 1, "wwt": 2154.1295999999998, "makespan": 166.7337, "mean_flow": 6.6146125, "breach_share": 0.0525, "breach_p1": 0.1652892561983471, "breach_p2": 0.0, "breach_p3": 0.013513513513513514, "breach_p4": 0.0, "wall_seconds": 0.0008124257437884808}, "pfifo": {"id": "c12_replay_400_0064_m1.25", "base_id": "c12_replay_400_0064", "campus": 12, "size": 400, "condition": "crew1.25", "sla_multiplier": 1.0, "crew_multiplier": 1.25, "method": "pfifo", "seed": 301, "feasible": 1, "wwt": 2154.1295999999998, "makespan": 166.7337, "mean_flow": 6.6146125, "breach_share": 0.0525, "breach_p1": 0.1652892561983471, "breach_p2": 0.0, "breach_p3": 0.013513513513513514, "breach_p4": 0.0, "wall_seconds": 0.0006178701296448708}, "mor": {"id": "c12_replay_400_0064_m1.25", "base_id": "c12_replay_400_0064", "campus": 12, "size": 400, "condition": "crew1.25", "sla_multiplier": 1.0, "crew_multiplier": 1.25, "method": "mor", "seed": 301, "feasible": 1, "wwt": 2154.1295999999998, "makespan": 166.7337, "mean_flow": 6.6146125, "breach_share": 0.0525, "breach_p1": 0.1652892561983471, "breach_p2": 0.0, "breach_p3": 0.013513513513513514, "breach_p4": 0.0, "wall_seconds": 0.0006260708905756474}, "random": {"id": "c12_replay_400_0064_m1.25", "base_id": "c12_replay_400_0064", "campus": 12, "size": 400, "condition": "crew1.25", "sla_multiplier": 1.0, "crew_multiplier": 1.25, "method": "random", "seed": 301, "feasible": 1, "wwt": 2154.1295999999998, "makespan": 166.7337, "mean_flow": 6.6146125, "breach_share": 0.0525, "breach_p1": 0.1652892561983471, "breach_p2": 0.0, "breach_p3": 0.013513513513513514, "breach_p4": 0.0, "wall_seconds": 0.000593382865190506}, "v2rl301": {"id": "c12_replay_400_0064_m1.25", "base_id": "c12_replay_400_0064", "campus": 12, "size": 400, "condition": "crew1.25", "sla_multiplier": 1.0, "crew_multiplier": 1.25, "method": "v2rl301", "seed": 301, "feasible": 1, "wwt": 2154.1295999999998, "makespan": 166.7337, "mean_flow": 6.6146125, "breach_share": 0.0525, "breach_p1": 0.1652892561983471, "breach_p2": 0.0, "breach_p3": 0.013513513513513514, "breach_p4": 0.0, "wall_seconds": 0.04098360612988472}, "v2rl302": {"id": "c12_replay_400_0064_m1.25", "base_id": "c12_replay_400_0064", "campus": 12, "size": 400, "condition": "crew1.25", "sla_multiplier": 1.0, "crew_multiplier": 1.25, "method": "v2rl302", "seed": 302, "feasible": 1, "wwt": 2154.1295999999998, "makespan": 166.7337, "mean_flow": 6.6146125, "breach_share": 0.0525, "breach_p1": 0.1652892561983471, "breach_p2": 0.0, "breach_p3": 0.013513513513513514, "breach_p4": 0.0, "wall_seconds": 0.04011246282607317}, "v2rl303": {"id": "c12_replay_400_0064_m1.25", "base_id": "c12_replay_400_0064", "campus": 12, "size": 400, "condition": "crew1.25", "sla_multiplier": 1.0, "crew_multiplier": 1.25, "method": "v2rl303", "seed": 303, "feasible": 1, "wwt": 2154.1295999999998, "makespan": 166.7337, "mean_flow": 6.6146125, "breach_share": 0.0525, "breach_p1": 0.1652892561983471, "breach_p2": 0.0, "breach_p3": 0.013513513513513514, "breach_p4": 0.0, "wall_seconds": 0.03993306402117014}}, "methods_expected": ["edd", "wspt", "atc", "pfifo", "mor", "random", "v2rl301", "v2rl302", "v2rl303"], "infeasible": [], "wall_seconds_total": 0.129657668992877}