{"id": "c01_gen_400_0020", "campus": "1", "track": "generator", "size": "400", "rows": {"edd": {"id": "c01_gen_400_0020", "campus": "1", "track": "generator", "size": "400", "method": "edd", "feasible": 1, "wwt": 102.66160000000002, "makespan": 107.7765, "mean_flow": 3.58894725, "breach_share": 0.0025, "breach_p1": 0.0, "breach_p2": 0.005263157894736842, "breach_p3": 0.0, "breach_p4": 0.0, "wall_seconds": 0.0009362669661641121, "decisions": 400, "status": "", "objective_bh": null, "best_bound_bh": null, "reused_from_60": false}, "wspt": {"id": "c01_gen_400_0020", "campus": "1", "track": "generator", "size": "400", "method": "wspt", "feasible": 1, "wwt": 102.66160000000002, "makespan": 107.7765, "mean_flow": 3.58894725, "breach_share": 0.0025, "breach_p1": 0.0, "breach_p2": 0.005263157894736842, "breach_p3": 0.0, "breach_p4": 0.0, "wall_seconds": 0.0008920407854020596, "decisions": 400, "status": "", "objective_bh": null, "best_bound_bh": null, "reused_from_60": false}, "atc": {"id": "c01_gen_400_0020", "campus": "1", "track": "generator", "size": "400", "method": "atc", "feasible": 1, "wwt": 102.66160000000002, "makespan": 107.7765, "mean_flow": 3.58894725, "breach_share": 0.0025, "breach_p1": 0.0, "breach_p2": 0.005263157894736842, "breach_p3": 0.0, "breach_p4": 0.0, "wall_seconds": 0.0011226269416511059, "decisions": 400, "status": "", "objective_bh": null, "best_bound_bh": null, "reused_from_60": false}, "pfifo": {"id": "c01_gen_400_0020", "campus": "1", "track": "generator", "size": "400", "method": "pfifo", "feasible": 1, "wwt": 102.66160000000002, "makespan": 107.7765, "mean_flow": 3.58894725, "breach_share": 0.0025, "breach_p1": 0.0, "breach_p2": 0.005263157894736842, "breach_p3": 0.0, "breach_p4": 0.0, "wall_seconds": 0.000866621732711792, "decisions": 400, "status": "", "objective_bh": null, "best_bound_bh": null, "reused_from_60": false}, "mor": {"id": "c01_gen_400_0020", "campus": "1", "track": "generator", "size": "400", "method": "mor", "feasible": 1, "wwt": 102.66160000000002, "makespan": 107.7765, "mean_flow": 3.58894725, "breach_share": 0.0025, "breach_p1": 0.0, "breach_p2": 0.005263157894736842, "breach_p3": 0.0, "breach_p4": 0.0, "wall_seconds": 0.0008640564046800137, "decisions": 400, "status": "", "objective_bh": null, "best_bound_bh": null, "reused_from_60": false}, "random": {"id": "c01_gen_400_0020", "campus": "1", "track": "generator", "size": "400", "method": "random", "feasible": 1, "wwt": 102.66160000000002, "makespan": 107.7765, "mean_flow": 3.58894725, "breach_share": 0.0025, "breach_p1": 0.0, "breach_p2": 0.005263157894736842, "breach_p3": 0.0, "breach_p4": 0.0, "wall_seconds": 0.0008784467354416847, "decisions": 400, "status": "", "objective_bh": null, "best_bound_bh": null, "reused_from_60": false}, "ga": {"id": "c01_gen_400_0020", "campus": "1", "track": "generator", "size": "400", "method": "ga", "feasible": 1, "wwt": 102.66160000000002, "makespan": 107.7765, "mean_flow": 3.58894725, "breach_share": 0.0025, "breach_p1": 0.0, "breach_p2": 0.005263157894736842, "breach_p3": 0.0, "breach_p4": 0.0, "wall_seconds": 6.57332514366135, "decisions": 19700, "status": "", "objective_bh": null, "best_bound_bh": null, "reused_from_60": false}, "cpsat60": {"id": "c01_gen_400_0020", "campus": "1", "track": "generator", "size": "400", "method": "cpsat60", "feasible": 1, "wwt": 102.69240000000002, "makespan": 107.78, "mean_flow": 3.593967, "breach_share": 0.0025, "breach_p1": 0.0, "breach_p2": 0.005263157894736842, "breach_p3": 0.0, "breach_p4": 0.0, "wall_seconds": 0.3367540300823748, "decisions": 12878, "status": "OPTIMAL", "objective_bh": 102.72, "best_bound_bh": 102.72, "reused_from_60": false}, "cpsat300": {"id": "c01_gen_400_0020", "campus": "1", "track": "generator", "size": "400", "method": "cpsat300", "feasible": 1, "wwt": 102.69240000000002, "makespan": 107.78, "mean_flow": 3.593967, "breach_share": 0.0025, "breach_p1": 0.0, "breach_p2": 0.005263157894736842, "breach_p3": 0.0, "breach_p4": 0.0, "wall_seconds": 0.3367540300823748, "decisions": 12878, "status": "OPTIMAL", "objective_bh": 102.72, "best_bound_bh": 102.72, "reused_from_60": true}}, "infeasible": [], "wall_seconds_total": 6.934175972826779}