{"id": "c02_gen_400_0059", "campus": "2", "track": "generator", "size": "400", "rows": {"edd": {"id": "c02_gen_400_0059", "campus": "2", "track": "generator", "size": "400", "method": "edd", "feasible": 1, "wwt": 642.3483999999999, "makespan": 595.1545, "mean_flow": 7.054003500000001, "breach_share": 0.0125, "breach_p1": 1.0, "breach_p2": 0.05084745762711865, "breach_p3": 0.01639344262295082, "breach_p4": 0.0, "wall_seconds": 0.0009387270547449589, "decisions": 400, "status": "", "objective_bh": null, "best_bound_bh": null, "reused_from_60": false}, "wspt": {"id": "c02_gen_400_0059", "campus": "2", "track": "generator", "size": "400", "method": "wspt", "feasible": 1, "wwt": 642.3483999999999, "makespan": 595.1545, "mean_flow": 7.054003500000001, "breach_share": 0.0125, "breach_p1": 1.0, "breach_p2": 0.05084745762711865, "breach_p3": 0.01639344262295082, "breach_p4": 0.0, "wall_seconds": 0.0008558076806366444, "decisions": 400, "status": "", "objective_bh": null, "best_bound_bh": null, "reused_from_60": false}, "atc": {"id": "c02_gen_400_0059", "campus": "2", "track": "generator", "size": "400", "method": "atc", "feasible": 1, "wwt": 642.3483999999999, "makespan": 595.1545, "mean_flow": 7.054003500000001, "breach_share": 0.0125, "breach_p1": 1.0, "breach_p2": 0.05084745762711865, "breach_p3": 0.01639344262295082, "breach_p4": 0.0, "wall_seconds": 0.0010473192669451237, "decisions": 400, "status": "", "objective_bh": null, "best_bound_bh": null, "reused_from_60": false}, "pfifo": {"id": "c02_gen_400_0059", "campus": "2", "track": "generator", "size": "400", "method": "pfifo", "feasible": 1, "wwt": 642.3483999999999, "makespan": 595.1545, "mean_flow": 7.054003500000001, "breach_share": 0.0125, "breach_p1": 1.0, "breach_p2": 0.05084745762711865, "breach_p3": 0.01639344262295082, "breach_p4": 0.0, "wall_seconds": 0.0008176839910447598, "decisions": 400, "status": "", "objective_bh": null, "best_bound_bh": null, "reused_from_60": false}, "mor": {"id": "c02_gen_400_0059", "campus": "2", "track": "generator", "size": "400", "method": "mor", "feasible": 1, "wwt": 642.3483999999999, "makespan": 595.1545, "mean_flow": 7.054003500000001, "breach_share": 0.0125, "breach_p1": 1.0, "breach_p2": 0.05084745762711865, "breach_p3": 0.01639344262295082, "breach_p4": 0.0, "wall_seconds": 0.000814101193100214, "decisions": 400, "status": "", "objective_bh": null, "best_bound_bh": null, "reused_from_60": false}, "random": {"id": "c02_gen_400_0059", "campus": "2", "track": "generator", "size": "400", "method": "random", "feasible": 1, "wwt": 642.3483999999999, "makespan": 595.1545, "mean_flow": 7.054003500000001, "breach_share": 0.0125, "breach_p1": 1.0, "breach_p2": 0.05084745762711865, "breach_p3": 0.01639344262295082, "breach_p4": 0.0, "wall_seconds": 0.0008460013195872307, "decisions": 400, "status": "", "objective_bh": null, "best_bound_bh": null, "reused_from_60": false}, "ga": {"id": "c02_gen_400_0059", "campus": "2", "track": "generator", "size": "400", "method": "ga", "feasible": 1, "wwt": 642.3483999999999, "makespan": 595.1545, "mean_flow": 7.054003500000001, "breach_share": 0.0125, "breach_p1": 1.0, "breach_p2": 0.05084745762711865, "breach_p3": 0.01639344262295082, "breach_p4": 0.0, "wall_seconds": 4.489405944943428, "decisions": 19700, "status": "", "objective_bh": null, "best_bound_bh": null, "reused_from_60": false}, "cpsat60": {"id": "c02_gen_400_0059", "campus": "2", "track": "generator", "size": "400", "method": "cpsat60", "feasible": 1, "wwt": 642.4375999999996, "makespan": 595.1605, "mean_flow": 7.0588370000000005, "breach_share": 0.0125, "breach_p1": 1.0, "breach_p2": 0.05084745762711865, "breach_p3": 0.01639344262295082, "breach_p4": 0.0, "wall_seconds": 0.1490000495687127, "decisions": 6239, "status": "OPTIMAL", "objective_bh": 642.54, "best_bound_bh": 642.54, "reused_from_60": false}, "cpsat300": {"id": "c02_gen_400_0059", "campus": "2", "track": "generator", "size": "400", "method": "cpsat300", "feasible": 1, "wwt": 642.4375999999996, "makespan": 595.1605, "mean_flow": 7.0588370000000005, "breach_share": 0.0125, "breach_p1": 1.0, "breach_p2": 0.05084745762711865, "breach_p3": 0.01639344262295082, "breach_p4": 0.0, "wall_seconds": 0.1490000495687127, "decisions": 6239, "status": "OPTIMAL", "objective_bh": 642.54, "best_bound_bh": 642.54, "reused_from_60": true}}, "infeasible": [], "wall_seconds_total": 4.65306803304702}