{"id": "c05_gen_50_0069", "campus": "5", "track": "generator", "size": "50", "rows": {"edd": {"id": "c05_gen_50_0069", "campus": "5", "track": "generator", "size": "50", "method": "edd", "feasible": 1, "wwt": 0.0, "makespan": 14.302999999999999, "mean_flow": 2.8233439999999996, "breach_share": 0.0, "breach_p1": null, "breach_p2": null, "breach_p3": 0.0, "breach_p4": 0.0, "wall_seconds": 0.00018066074699163437, "decisions": 50, "status": "", "objective_bh": null, "best_bound_bh": null, "reused_from_60": false}, "wspt": {"id": "c05_gen_50_0069", "campus": "5", "track": "generator", "size": "50", "method": "wspt", "feasible": 1, "wwt": 0.0, "makespan": 14.302999999999999, "mean_flow": 2.820458, "breach_share": 0.0, "breach_p1": null, "breach_p2": null, "breach_p3": 0.0, "breach_p4": 0.0, "wall_seconds": 0.00015607615932822227, "decisions": 50, "status": "", "objective_bh": null, "best_bound_bh": null, "reused_from_60": false}, "atc": {"id": "c05_gen_50_0069", "campus": "5", "track": "generator", "size": "50", "method": "atc", "feasible": 1, "wwt": 0.0, "makespan": 14.302999999999999, "mean_flow": 2.8212759999999997, "breach_share": 0.0, "breach_p1": null, "breach_p2": null, "breach_p3": 0.0, "breach_p4": 0.0, "wall_seconds": 0.00018881075084209442, "decisions": 50, "status": "", "objective_bh": null, "best_bound_bh": null, "reused_from_60": false}, "pfifo": {"id": "c05_gen_50_0069", "campus": "5", "track": "generator", "size": "50", "method": "pfifo", "feasible": 1, "wwt": 0.0, "makespan": 14.302999999999999, "mean_flow": 2.8233439999999996, "breach_share": 0.0, "breach_p1": null, "breach_p2": null, "breach_p3": 0.0, "breach_p4": 0.0, "wall_seconds": 0.0001518242061138153, "decisions": 50, "status": "", "objective_bh": null, "best_bound_bh": null, "reused_from_60": false}, "mor": {"id": "c05_gen_50_0069", "campus": "5", "track": "generator", "size": "50", "method": "mor", "feasible": 1, "wwt": 0.0, "makespan": 14.302999999999999, "mean_flow": 2.8245940000000003, "breach_share": 0.0, "breach_p1": null, "breach_p2": null, "breach_p3": 0.0, "breach_p4": 0.0, "wall_seconds": 0.00014585023745894432, "decisions": 50, "status": "", "objective_bh": null, "best_bound_bh": null, "reused_from_60": false}, "random": {"id": "c05_gen_50_0069", "campus": "5", "track": "generator", "size": "50", "method": "random", "feasible": 1, "wwt": 0.0, "makespan": 14.302999999999999, "mean_flow": 2.8217079999999997, "breach_share": 0.0, "breach_p1": null, "breach_p2": null, "breach_p3": 0.0, "breach_p4": 0.0, "wall_seconds": 0.000147129874676466, "decisions": 50, "status": "", "objective_bh": null, "best_bound_bh": null, "reused_from_60": false}, "ga": {"id": "c05_gen_50_0069", "campus": "5", "track": "generator", "size": "50", "method": "ga", "feasible": 1, "wwt": 0.0, "makespan": 14.302999999999999, "mean_flow": 2.8233439999999996, "breach_share": 0.0, "breach_p1": null, "breach_p2": null, "breach_p3": 0.0, "breach_p4": 0.0, "wall_seconds": 0.5520347021520138, "decisions": 19700, "status": "", "objective_bh": null, "best_bound_bh": null, "reused_from_60": false}, "cpsat60": {"id": "c05_gen_50_0069", "campus": "5", "track": "generator", "size": "50", "method": "cpsat60", "feasible": 1, "wwt": 0.0, "makespan": 14.4587, "mean_flow": 3.011262, "breach_share": 0.0, "breach_p1": null, "breach_p2": null, "breach_p3": 0.0, "breach_p4": 0.0, "wall_seconds": 0.06126299174502492, "decisions": 2836, "status": "OPTIMAL", "objective_bh": 0.0, "best_bound_bh": 0.0, "reused_from_60": false}, "cpsat300": {"id": "c05_gen_50_0069", "campus": "5", "track": "generator", "size": "50", "method": "cpsat300", "feasible": 1, "wwt": 0.0, "makespan": 14.4587, "mean_flow": 3.011262, "breach_share": 0.0, "breach_p1": null, "breach_p2": null, "breach_p3": 0.0, "breach_p4": 0.0, "wall_seconds": 0.06126299174502492, "decisions": 2836, "status": "OPTIMAL", "objective_bh": 0.0, "best_bound_bh": 0.0, "reused_from_60": true}}, "infeasible": [], "wall_seconds_total": 0.6187172993086278}