{"id": "c09_gen_400_0074", "campus": "9", "track": "generator", "size": "400", "rows": {"edd": {"id": "c09_gen_400_0074", "campus": "9", "track": "generator", "size": "400", "method": "edd", "feasible": 1, "wwt": 14.177999999999997, "makespan": 93.9212, "mean_flow": 3.241349, "breach_share": 0.0025, "breach_p1": 0.0, "breach_p2": 0.014285714285714285, "breach_p3": 0.0, "breach_p4": 0.0, "wall_seconds": 0.0009362720884382725, "decisions": 400, "status": "", "objective_bh": null, "best_bound_bh": null, "reused_from_60": false}, "wspt": {"id": "c09_gen_400_0074", "campus": "9", "track": "generator", "size": "400", "method": "wspt", "feasible": 1, "wwt": 14.177999999999997, "makespan": 93.9212, "mean_flow": 3.241349, "breach_share": 0.0025, "breach_p1": 0.0, "breach_p2": 0.014285714285714285, "breach_p3": 0.0, "breach_p4": 0.0, "wall_seconds": 0.0008868910372257233, "decisions": 400, "status": "", "objective_bh": null, "best_bound_bh": null, "reused_from_60": false}, "atc": {"id": "c09_gen_400_0074", "campus": "9", "track": "generator", "size": "400", "method": "atc", "feasible": 1, "wwt": 14.177999999999997, "makespan": 93.9212, "mean_flow": 3.241349, "breach_share": 0.0025, "breach_p1": 0.0, "breach_p2": 0.014285714285714285, "breach_p3": 0.0, "breach_p4": 0.0, "wall_seconds": 0.0010913009755313396, "decisions": 400, "status": "", "objective_bh": null, "best_bound_bh": null, "reused_from_60": false}, "pfifo": {"id": "c09_gen_400_0074", "campus": "9", "track": "generator", "size": "400", "method": "pfifo", "feasible": 1, "wwt": 14.177999999999997, "makespan": 93.9212, "mean_flow": 3.241349, "breach_share": 0.0025, "breach_p1": 0.0, "breach_p2": 0.014285714285714285, "breach_p3": 0.0, "breach_p4": 0.0, "wall_seconds": 0.0008574230596423149, "decisions": 400, "status": "", "objective_bh": null, "best_bound_bh": null, "reused_from_60": false}, "mor": {"id": "c09_gen_400_0074", "campus": "9", "track": "generator", "size": "400", "method": "mor", "feasible": 1, "wwt": 14.177999999999997, "makespan": 93.9212, "mean_flow": 3.241349, "breach_share": 0.0025, "breach_p1": 0.0, "breach_p2": 0.014285714285714285, "breach_p3": 0.0, "breach_p4": 0.0, "wall_seconds": 0.0008451552130281925, "decisions": 400, "status": "", "objective_bh": null, "best_bound_bh": null, "reused_from_60": false}, "random": {"id": "c09_gen_400_0074", "campus": "9", "track": "generator", "size": "400", "method": "random", "feasible": 1, "wwt": 14.177999999999997, "makespan": 93.9212, "mean_flow": 3.241349, "breach_share": 0.0025, "breach_p1": 0.0, "breach_p2": 0.014285714285714285, "breach_p3": 0.0, "breach_p4": 0.0, "wall_seconds": 0.0006848219782114029, "decisions": 400, "status": "", "objective_bh": null, "best_bound_bh": null, "reused_from_60": false}, "ga": {"id": "c09_gen_400_0074", "campus": "9", "track": "generator", "size": "400", "method": "ga", "feasible": 1, "wwt": 14.177999999999997, "makespan": 93.9212, "mean_flow": 3.241349, "breach_share": 0.0025, "breach_p1": 0.0, "breach_p2": 0.014285714285714285, "breach_p3": 0.0, "breach_p4": 0.0, "wall_seconds": 5.51931165298447, "decisions": 19700, "status": "", "objective_bh": null, "best_bound_bh": null, "reused_from_60": false}, "cpsat60": {"id": "c09_gen_400_0074", "campus": "9", "track": "generator", "size": "400", "method": "cpsat60", "feasible": 1, "wwt": 14.197199999999953, "makespan": 93.92679999999999, "mean_flow": 3.24623925, "breach_share": 0.0025, "breach_p1": 0.0, "breach_p2": 0.014285714285714285, "breach_p3": 0.0, "breach_p4": 0.0, "wall_seconds": 0.3462979639880359, "decisions": 13372, "status": "OPTIMAL", "objective_bh": 14.2, "best_bound_bh": 14.2, "reused_from_60": false}, "cpsat300": {"id": "c09_gen_400_0074", "campus": "9", "track": "generator", "size": "400", "method": "cpsat300", "feasible": 1, "wwt": 14.197199999999953, "makespan": 93.92679999999999, "mean_flow": 3.24623925, "breach_share": 0.0025, "breach_p1": 0.0, "breach_p2": 0.014285714285714285, "breach_p3": 0.0, "breach_p4": 0.0, "wall_seconds": 0.3462979639880359, "decisions": 13372, "status": "OPTIMAL", "objective_bh": 14.2, "best_bound_bh": 14.2, "reused_from_60": true}}, "infeasible": [], "wall_seconds_total": 5.887221449054778}