{"id": "c12_replay_150_0107", "campus": "12", "track": "replay", "size": "150", "rows": {"edd": {"id": "c12_replay_150_0107", "campus": "12", "track": "replay", "size": "150", "method": "edd", "feasible": 1, "wwt": 421.7296, "makespan": 98.1862, "mean_flow": 7.298629333333333, "breach_share": 0.03333333333333333, "breach_p1": 0.19047619047619047, "breach_p2": 0.0, "breach_p3": 0.030303030303030304, "breach_p4": 0.0, "wall_seconds": 0.0003010351210832596, "decisions": 150, "status": "", "objective_bh": null, "best_bound_bh": null, "reused_from_60": false}, "wspt": {"id": "c12_replay_150_0107", "campus": "12", "track": "replay", "size": "150", "method": "wspt", "feasible": 1, "wwt": 421.7296, "makespan": 98.1862, "mean_flow": 7.298629333333333, "breach_share": 0.03333333333333333, "breach_p1": 0.19047619047619047, "breach_p2": 0.0, "breach_p3": 0.030303030303030304, "breach_p4": 0.0, "wall_seconds": 0.00028713932260870934, "decisions": 150, "status": "", "objective_bh": null, "best_bound_bh": null, "reused_from_60": false}, "atc": {"id": "c12_replay_150_0107", "campus": "12", "track": "replay", "size": "150", "method": "atc", "feasible": 1, "wwt": 421.7296, "makespan": 98.1862, "mean_flow": 7.298629333333333, "breach_share": 0.03333333333333333, "breach_p1": 0.19047619047619047, "breach_p2": 0.0, "breach_p3": 0.030303030303030304, "breach_p4": 0.0, "wall_seconds": 0.0003746901638805866, "decisions": 150, "status": "", "objective_bh": null, "best_bound_bh": null, "reused_from_60": false}, "pfifo": {"id": "c12_replay_150_0107", "campus": "12", "track": "replay", "size": "150", "method": "pfifo", "feasible": 1, "wwt": 421.7296, "makespan": 98.1862, "mean_flow": 7.298629333333333, "breach_share": 0.03333333333333333, "breach_p1": 0.19047619047619047, "breach_p2": 0.0, "breach_p3": 0.030303030303030304, "breach_p4": 0.0, "wall_seconds": 0.0002806801348924637, "decisions": 150, "status": "", "objective_bh": null, "best_bound_bh": null, "reused_from_60": false}, "mor": {"id": "c12_replay_150_0107", "campus": "12", "track": "replay", "size": "150", "method": "mor", "feasible": 1, "wwt": 421.7296, "makespan": 98.1862, "mean_flow": 7.298629333333333, "breach_share": 0.03333333333333333, "breach_p1": 0.19047619047619047, "breach_p2": 0.0, "breach_p3": 0.030303030303030304, "breach_p4": 0.0, "wall_seconds": 0.0002791881561279297, "decisions": 150, "status": "", "objective_bh": null, "best_bound_bh": null, "reused_from_60": false}, "random": {"id": "c12_replay_150_0107", "campus": "12", "track": "replay", "size": "150", "method": "random", "feasible": 1, "wwt": 421.7296, "makespan": 98.1862, "mean_flow": 7.298629333333333, "breach_share": 0.03333333333333333, "breach_p1": 0.19047619047619047, "breach_p2": 0.0, "breach_p3": 0.030303030303030304, "breach_p4": 0.0, "wall_seconds": 0.0002639717422425747, "decisions": 150, "status": "", "objective_bh": null, "best_bound_bh": null, "reused_from_60": false}, "ga": {"id": "c12_replay_150_0107", "campus": "12", "track": "replay", "size": "150", "method": "ga", "feasible": 1, "wwt": 421.7296, "makespan": 98.1862, "mean_flow": 7.298629333333333, "breach_share": 0.03333333333333333, "breach_p1": 0.19047619047619047, "breach_p2": 0.0, "breach_p3": 0.030303030303030304, "breach_p4": 0.0, "wall_seconds": 2.096549076028168, "decisions": 19700, "status": "", "objective_bh": null, "best_bound_bh": null, "reused_from_60": false}, "cpsat60": {"id": "c12_replay_150_0107", "campus": "12", "track": "replay", "size": "150", "method": "cpsat60", "feasible": 1, "wwt": 421.9782, "makespan": 98.1948, "mean_flow": 7.302459999999999, "breach_share": 0.04666666666666667, "breach_p1": 0.2857142857142857, "breach_p2": 0.0, "breach_p3": 0.030303030303030304, "breach_p4": 0.0, "wall_seconds": 0.22423675702884793, "decisions": 19980, "status": "OPTIMAL", "objective_bh": 421.98, "best_bound_bh": 421.98, "reused_from_60": false}, "cpsat300": {"id": "c12_replay_150_0107", "campus": "12", "track": "replay", "size": "150", "method": "cpsat300", "feasible": 1, "wwt": 421.9782, "makespan": 98.1948, "mean_flow": 7.302459999999999, "breach_share": 0.04666666666666667, "breach_p1": 0.2857142857142857, "breach_p2": 0.0, "breach_p3": 0.030303030303030304, "breach_p4": 0.0, "wall_seconds": 0.22423675702884793, "decisions": 19980, "status": "OPTIMAL", "objective_bh": 421.98, "best_bound_bh": 421.98, "reused_from_60": true}}, "infeasible": [], "wall_seconds_total": 2.3273188159801066}