{"id": "c12_gen_50_0027", "campus": "12", "track": "generator", "size": "50", "rows": {"edd": {"id": "c12_gen_50_0027", "campus": "12", "track": "generator", "size": "50", "method": "edd", "feasible": 1, "wwt": 1.0232000000000028, "makespan": 17.1663, "mean_flow": 3.0435940000000006, "breach_share": 0.02, "breach_p1": 0.14285714285714285, "breach_p2": 0.0, "breach_p3": 0.0, "breach_p4": 0.0, "wall_seconds": 0.0001575700007379055, "decisions": 50, "status": "", "objective_bh": null, "best_bound_bh": null, "reused_from_60": false}, "wspt": {"id": "c12_gen_50_0027", "campus": "12", "track": "generator", "size": "50", "method": "wspt", "feasible": 1, "wwt": 1.0232000000000028, "makespan": 17.1663, "mean_flow": 3.0435940000000006, "breach_share": 0.02, "breach_p1": 0.14285714285714285, "breach_p2": 0.0, "breach_p3": 0.0, "breach_p4": 0.0, "wall_seconds": 0.00013342639431357384, "decisions": 50, "status": "", "objective_bh": null, "best_bound_bh": null, "reused_from_60": false}, "atc": {"id": "c12_gen_50_0027", "campus": "12", "track": "generator", "size": "50", "method": "atc", "feasible": 1, "wwt": 1.0232000000000028, "makespan": 17.1663, "mean_flow": 3.0435940000000006, "breach_share": 0.02, "breach_p1": 0.14285714285714285, "breach_p2": 0.0, "breach_p3": 0.0, "breach_p4": 0.0, "wall_seconds": 0.00015526730567216873, "decisions": 50, "status": "", "objective_bh": null, "best_bound_bh": null, "reused_from_60": false}, "pfifo": {"id": "c12_gen_50_0027", "campus": "12", "track": "generator", "size": "50", "method": "pfifo", "feasible": 1, "wwt": 1.0232000000000028, "makespan": 17.1663, "mean_flow": 3.0435940000000006, "breach_share": 0.02, "breach_p1": 0.14285714285714285, "breach_p2": 0.0, "breach_p3": 0.0, "breach_p4": 0.0, "wall_seconds": 0.00012674322351813316, "decisions": 50, "status": "", "objective_bh": null, "best_bound_bh": null, "reused_from_60": false}, "mor": {"id": "c12_gen_50_0027", "campus": "12", "track": "generator", "size": "50", "method": "mor", "feasible": 1, "wwt": 1.0232000000000028, "makespan": 17.1663, "mean_flow": 3.0435940000000006, "breach_share": 0.02, "breach_p1": 0.14285714285714285, "breach_p2": 0.0, "breach_p3": 0.0, "breach_p4": 0.0, "wall_seconds": 0.0001253862865269184, "decisions": 50, "status": "", "objective_bh": null, "best_bound_bh": null, "reused_from_60": false}, "random": {"id": "c12_gen_50_0027", "campus": "12", "track": "generator", "size": "50", "method": "random", "feasible": 1, "wwt": 1.0232000000000028, "makespan": 17.1663, "mean_flow": 3.0435940000000006, "breach_share": 0.02, "breach_p1": 0.14285714285714285, "breach_p2": 0.0, "breach_p3": 0.0, "breach_p4": 0.0, "wall_seconds": 0.0001251990906894207, "decisions": 50, "status": "", "objective_bh": null, "best_bound_bh": null, "reused_from_60": false}, "ga": {"id": "c12_gen_50_0027", "campus": "12", "track": "generator", "size": "50", "method": "ga", "feasible": 1, "wwt": 1.0232000000000028, "makespan": 17.1663, "mean_flow": 3.0435940000000006, "breach_share": 0.02, "breach_p1": 0.14285714285714285, "breach_p2": 0.0, "breach_p3": 0.0, "breach_p4": 0.0, "wall_seconds": 0.48957572784274817, "decisions": 19700, "status": "", "objective_bh": null, "best_bound_bh": null, "reused_from_60": false}, "cpsat60": {"id": "c12_gen_50_0027", "campus": "12", "track": "generator", "size": "50", "method": "cpsat60", "feasible": 1, "wwt": 1.0888000000000062, "makespan": 17.1672, "mean_flow": 3.1993840000000002, "breach_share": 0.02, "breach_p1": 0.14285714285714285, "breach_p2": 0.0, "breach_p3": 0.0, "breach_p4": 0.0, "wall_seconds": 0.06444233609363437, "decisions": 9760, "status": "OPTIMAL", "objective_bh": 1.12, "best_bound_bh": 1.12, "reused_from_60": false}, "cpsat300": {"id": "c12_gen_50_0027", "campus": "12", "track": "generator", "size": "50", "method": "cpsat300", "feasible": 1, "wwt": 1.0888000000000062, "makespan": 17.1672, "mean_flow": 3.1993840000000002, "breach_share": 0.02, "breach_p1": 0.14285714285714285, "breach_p2": 0.0, "breach_p3": 0.0, "breach_p4": 0.0, "wall_seconds": 0.06444233609363437, "decisions": 9760, "status": "OPTIMAL", "objective_bh": 1.12, "best_bound_bh": 1.12, "reused_from_60": true}}, "infeasible": [], "wall_seconds_total": 0.5596589301712811}