{"id": "c12_replay_50_0178", "campus": "12", "track": "replay", "size": "50", "rows": {"edd": {"id": "c12_replay_50_0178", "campus": "12", "track": "replay", "size": "50", "method": "edd", "feasible": 1, "wwt": 160.0, "makespan": 90.8648, "mean_flow": 8.832296, "breach_share": 0.04, "breach_p1": 0.1111111111111111, "breach_p2": 0.1, "breach_p3": 0.0, "breach_p4": 0.0, "wall_seconds": 0.00022412510588765144, "decisions": 50, "status": "", "objective_bh": null, "best_bound_bh": null, "reused_from_60": false}, "wspt": {"id": "c12_replay_50_0178", "campus": "12", "track": "replay", "size": "50", "method": "wspt", "feasible": 1, "wwt": 160.0, "makespan": 90.8648, "mean_flow": 8.832296, "breach_share": 0.04, "breach_p1": 0.1111111111111111, "breach_p2": 0.1, "breach_p3": 0.0, "breach_p4": 0.0, "wall_seconds": 0.00019948091357946396, "decisions": 50, "status": "", "objective_bh": null, "best_bound_bh": null, "reused_from_60": false}, "atc": {"id": "c12_replay_50_0178", "campus": "12", "track": "replay", "size": "50", "method": "atc", "feasible": 1, "wwt": 160.0, "makespan": 90.8648, "mean_flow": 8.832296, "breach_share": 0.04, "breach_p1": 0.1111111111111111, "breach_p2": 0.1, "breach_p3": 0.0, "breach_p4": 0.0, "wall_seconds": 0.00022344524040818214, "decisions": 50, "status": "", "objective_bh": null, "best_bound_bh": null, "reused_from_60": false}, "pfifo": {"id": "c12_replay_50_0178", "campus": "12", "track": "replay", "size": "50", "method": "pfifo", "feasible": 1, "wwt": 160.0, "makespan": 90.8648, "mean_flow": 8.832296, "breach_share": 0.04, "breach_p1": 0.1111111111111111, "breach_p2": 0.1, "breach_p3": 0.0, "breach_p4": 0.0, "wall_seconds": 0.00017772288993000984, "decisions": 50, "status": "", "objective_bh": null, "best_bound_bh": null, "reused_from_60": false}, "mor": {"id": "c12_replay_50_0178", "campus": "12", "track": "replay", "size": "50", "method": "mor", "feasible": 1, "wwt": 160.0, "makespan": 90.8648, "mean_flow": 8.832296, "breach_share": 0.04, "breach_p1": 0.1111111111111111, "breach_p2": 0.1, "breach_p3": 0.0, "breach_p4": 0.0, "wall_seconds": 0.0001735021360218525, "decisions": 50, "status": "", "objective_bh": null, "best_bound_bh": null, "reused_from_60": false}, "random": {"id": "c12_replay_50_0178", "campus": "12", "track": "replay", "size": "50", "method": "random", "feasible": 1, "wwt": 160.0, "makespan": 90.8648, "mean_flow": 8.832296, "breach_share": 0.04, "breach_p1": 0.1111111111111111, "breach_p2": 0.1, "breach_p3": 0.0, "breach_p4": 0.0, "wall_seconds": 0.0001753140240907669, "decisions": 50, "status": "", "objective_bh": null, "best_bound_bh": null, "reused_from_60": false}, "ga": {"id": "c12_replay_50_0178", "campus": "12", "track": "replay", "size": "50", "method": "ga", "feasible": 1, "wwt": 160.0, "makespan": 90.8648, "mean_flow": 8.832296, "breach_share": 0.04, "breach_p1": 0.1111111111111111, "breach_p2": 0.1, "breach_p3": 0.0, "breach_p4": 0.0, "wall_seconds": 0.5444245492108166, "decisions": 19700, "status": "", "objective_bh": null, "best_bound_bh": null, "reused_from_60": false}, "cpsat60": {"id": "c12_replay_50_0178", "campus": "12", "track": "replay", "size": "50", "method": "cpsat60", "feasible": 1, "wwt": 160.1008, "makespan": 145.03, "mean_flow": 15.211822, "breach_share": 0.04, "breach_p1": 0.1111111111111111, "breach_p2": 0.1, "breach_p3": 0.0, "breach_p4": 0.0, "wall_seconds": 0.06990001769736409, "decisions": 7968, "status": "OPTIMAL", "objective_bh": 160.12, "best_bound_bh": 160.12, "reused_from_60": false}, "cpsat300": {"id": "c12_replay_50_0178", "campus": "12", "track": "replay", "size": "50", "method": "cpsat300", "feasible": 1, "wwt": 160.1008, "makespan": 145.03, "mean_flow": 15.211822, "breach_share": 0.04, "breach_p1": 0.1111111111111111, "breach_p2": 0.1, "breach_p3": 0.0, "breach_p4": 0.0, "wall_seconds": 0.06990001769736409, "decisions": 7968, "status": "OPTIMAL", "objective_bh": 160.12, "best_bound_bh": 160.12, "reused_from_60": true}}, "infeasible": [], "wall_seconds_total": 0.6201509232632816}